potoos/__init__.py
potoos/client.py
potoos/models/__init__.py
potoos/models/anomaly.py
potoos/models/config.py
potoos-0.1.1.dist-info/LICENSE
potoos-0.1.1.dist-info/METADATA
potoos-0.1.1.dist-info/WHEEL
potoos-0.1.1.dist-info/top_level.txt
potoos-0.1.1.dist-info/RECORD
