Metadata-Version: 2.2
Name: potoos
Version: 0.1.1
Summary: Time series anomaly detection using Redis TimeSeries and Luminol
Author-email: Alexis Franche <alexis199807@live.ca>
Maintainer-email: Alexis Franche <alexis199807@live.ca>
License: MIT
Project-URL: Homepage, https://github.com/afranche7/Potoos
Keywords: redis,timeseries,redistimeseries,anomaly-detection,monitoring,luminol
Classifier: Development Status :: 4 - Beta
Classifier: Intended Audience :: Developers
Classifier: License :: OSI Approved :: MIT License
Classifier: Programming Language :: Python :: 3.10
Classifier: Programming Language :: Python :: 3.11
Classifier: Programming Language :: Python :: 3.12
Requires-Python: >=3.10
License-File: LICENSE
Requires-Dist: redis>=5.2.1
Requires-Dist: luminol>=0.4
Requires-Dist: numpy<=1.22.4
